Metadata-Version: 1.0
Name: luanaBanana-distributions
Version: 0.1
Summary: Gaussian luanaBanana_distributions
Home-page: UNKNOWN
Author: UNKNOWN
Author-email: UNKNOWN
License: UNKNOWN
Platform: UNKNOWN
